Metadata-Version: 2.1
Name: fanparsai
Version: 0.0.13
Summary: FanPars Library for Various Models
Author: FanPars
Requires-Dist: asteroid-filterbanks==0.4.0
